[
  {
    "line": 2,
    "elements": [
      {
        "start_timestamp": "2022-06-18T21:23:41.674Z",
        "before": [
          {
            "result": {
              "duration": 997500,
              "status": "passed"
            },
            "match": {
              "location": "com.spriteCloud.stepDefinitions.Hooks.setUp()"
            }
          }
        ],
        "line": 6,
        "name": "Verify that the user able to click the button",
        "description": "",
        "id": "click;verify-that-the-user-able-to-click-the-button",
        "after": [
          {
            "result": {
              "duration": 710632100,
              "status": "passed"
            },
            "match": {
              "location": "com.spriteCloud.stepDefinitions.Hooks.tearDown(io.cucumber.java.Scenario)"
            }
          }
        ],
        "type": "scenario",
        "keyword": "Scenario",
        "steps": [
          {
            "result": {
              "duration": 4855762500,
              "status": "passed"
            },
            "line": 7,
            "name": "the user is on the page",
            "match": {
              "location": "com.spriteCloud.stepDefinitions.ClickStepDefinition.the_user_is_on_the_page()"
            },
            "keyword": "Given "
          },
          {
            "result": {
              "duration": 337321700,
              "status": "passed"
            },
            "line": 8,
            "name": "the user clicks on the \"Click\" headline",
            "match": {
              "arguments": [
                {
                  "val": "\"Click\"",
                  "offset": 23
                }
              ],
              "location": "com.spriteCloud.stepDefinitions.ClickStepDefinition.the_user_clicks_on_the_headline(java.lang.String)"
            },
            "keyword": "When "
          },
          {
            "result": {
              "duration": 35868600,
              "status": "passed"
            },
            "line": 9,
            "name": "the window title contains \"Click\"",
            "match": {
              "arguments": [
                {
                  "val": "\"Click\"",
                  "offset": 26
                }
              ],
              "location": "com.spriteCloud.stepDefinitions.ClickStepDefinition.the_window_title_contains(java.lang.String)"
            },
            "keyword": "Then "
          },
          {
            "result": {
              "duration": 73714500,
              "status": "passed"
            },
            "line": 10,
            "name": "the user should see the following headlines",
            "match": {
              "location": "com.spriteCloud.stepDefinitions.ClickStepDefinition.the_user_should_see_the_following_headlines(java.util.List\u003cjava.lang.String\u003e)"
            },
            "rows": [
              {
                "cells": [
                  "Scenario"
                ]
              },
              {
                "cells": [
                  "Playground"
                ]
              }
            ],
            "keyword": "And "
          },
          {
            "result": {
              "duration": 66821500,
              "status": "passed"
            },
            "line": 13,
            "name": "the button is displayed",
            "match": {
              "location": "com.spriteCloud.stepDefinitions.ClickStepDefinition.the_button_is_displayed()"
            },
            "keyword": "And "
          },
          {
            "result": {
              "duration": 209622300,
              "status": "passed"
            },
            "line": 14,
            "name": "the user clicks on the button",
            "match": {
              "location": "com.spriteCloud.stepDefinitions.ClickStepDefinition.the_user_clicks_on_the_button()"
            },
            "keyword": "When "
          },
          {
            "result": {
              "duration": 64633400,
              "status": "passed"
            },
            "line": 15,
            "name": "the user should see the green button",
            "match": {
              "location": "com.spriteCloud.stepDefinitions.ClickStepDefinition.the_user_should_see_the_button()"
            },
            "keyword": "Then "
          }
        ],
        "tags": [
          {
            "name": "@ui"
          },
          {
            "name": "@click"
          }
        ]
      }
    ],
    "name": "Click",
    "description": "  US: As a user, I should able to click",
    "id": "click",
    "keyword": "Feature",
    "uri": "file:src/test/resources/features/Click.feature",
    "tags": [
      {
        "name": "@ui",
        "type": "Tag",
        "location": {
          "line": 1,
          "column": 1
        }
      }
    ]
  },
  {
    "line": 2,
    "elements": [
      {
        "start_timestamp": "2022-06-18T21:23:48.094Z",
        "before": [
          {
            "result": {
              "status": "passed"
            },
            "match": {
              "location": "com.spriteCloud.stepDefinitions.Hooks.setUp()"
            }
          }
        ],
        "line": 5,
        "name": "Get request for pet endpoint",
        "description": "",
        "id": "pet;get-request-for-pet-endpoint",
        "after": [
          {
            "result": {
              "status": "passed"
            },
            "match": {
              "location": "com.spriteCloud.stepDefinitions.Hooks.tearDown(io.cucumber.java.Scenario)"
            }
          }
        ],
        "type": "scenario",
        "keyword": "Scenario",
        "steps": [
          {
            "result": {
              "duration": 11969300,
              "status": "passed"
            },
            "line": 7,
            "name": "the endpoint is \"pet/1\"",
            "match": {
              "arguments": [
                {
                  "val": "\"pet/1\"",
                  "offset": 16
                }
              ],
              "location": "com.spriteCloud.stepDefinitions.BaseAPIStepDefinition.the_endpoint_is(java.lang.String)"
            },
            "keyword": "Given "
          },
          {
            "result": {
              "duration": 2233641300,
              "status": "passed"
            },
            "line": 8,
            "name": "I send GET Request",
            "match": {
              "location": "com.spriteCloud.stepDefinitions.BaseAPIStepDefinition.i_send_GET_Request()"
            },
            "keyword": "When "
          },
          {
            "result": {
              "duration": 27926700,
              "status": "passed"
            },
            "line": 9,
            "name": "the status code is 200",
            "match": {
              "arguments": [
                {
                  "val": "200",
                  "offset": 19
                }
              ],
              "location": "com.spriteCloud.stepDefinitions.BaseAPIStepDefinition.the_status_code_is(java.lang.Integer)"
            },
            "keyword": "Then "
          },
          {
            "result": {
              "duration": 572470100,
              "status": "passed"
            },
            "line": 10,
            "name": "the response body is the following",
            "match": {
              "location": "com.spriteCloud.stepDefinitions.PetStepDefinitions.the_response_body_is_the_following(java.util.List\u003cjava.util.Map\u003cjava.lang.String, java.lang.Object\u003e\u003e)"
            },
            "rows": [
              {
                "cells": [
                  "id",
                  "name",
                  "status"
                ]
              },
              {
                "cells": [
                  "1",
                  "doggie",
                  "available"
                ]
              }
            ],
            "keyword": "And "
          }
        ],
        "tags": [
          {
            "name": "@api"
          },
          {
            "name": "@pet"
          }
        ]
      }
    ],
    "name": "Pet",
    "description": "",
    "id": "pet",
    "keyword": "Feature",
    "uri": "file:src/test/resources/features/Pet.feature",
    "tags": [
      {
        "name": "@api",
        "type": "Tag",
        "location": {
          "line": 1,
          "column": 1
        }
      }
    ]
  },
  {
    "line": 2,
    "elements": [
      {
        "start_timestamp": "2022-06-18T21:23:50.955Z",
        "before": [
          {
            "result": {
              "status": "passed"
            },
            "match": {
              "location": "com.spriteCloud.stepDefinitions.Hooks.setUp()"
            }
          }
        ],
        "line": 5,
        "name": "Verify that the user able to login",
        "description": "",
        "id": "sample-app;verify-that-the-user-able-to-login",
        "after": [
          {
            "result": {
              "duration": 743551900,
              "status": "passed"
            },
            "match": {
              "location": "com.spriteCloud.stepDefinitions.Hooks.tearDown(io.cucumber.java.Scenario)"
            }
          }
        ],
        "type": "scenario",
        "keyword": "Scenario",
        "steps": [
          {
            "result": {
              "duration": 4108494400,
              "status": "passed"
            },
            "line": 6,
            "name": "the user is on the page",
            "match": {
              "location": "com.spriteCloud.stepDefinitions.ClickStepDefinition.the_user_is_on_the_page()"
            },
            "keyword": "Given "
          },
          {
            "result": {
              "duration": 332650600,
              "status": "passed"
            },
            "line": 7,
            "name": "the user clicks on the \"Sample App\" headline",
            "match": {
              "arguments": [
                {
                  "val": "\"Sample App\"",
                  "offset": 23
                }
              ],
              "location": "com.spriteCloud.stepDefinitions.ClickStepDefinition.the_user_clicks_on_the_headline(java.lang.String)"
            },
            "keyword": "When "
          },
          {
            "result": {
              "duration": 24963100,
              "status": "passed"
            },
            "line": 8,
            "name": "the window title contains \"Sample App\"",
            "match": {
              "arguments": [
                {
                  "val": "\"Sample App\"",
                  "offset": 26
                }
              ],
              "location": "com.spriteCloud.stepDefinitions.ClickStepDefinition.the_window_title_contains(java.lang.String)"
            },
            "keyword": "Then "
          },
          {
            "result": {
              "duration": 158656500,
              "status": "passed"
            },
            "line": 9,
            "name": "the user enters the following credentials",
            "match": {
              "location": "com.spriteCloud.stepDefinitions.SampleAppStepDefinition.the_user_enters_the_following_credentials(java.util.Map\u003cjava.lang.String, java.lang.String\u003e)"
            },
            "rows": [
              {
                "cells": [
                  "username",
                  "User Name"
                ]
              },
              {
                "cells": [
                  "password",
                  "pwd"
                ]
              }
            ],
            "keyword": "When "
          },
          {
            "result": {
              "duration": 132394200,
              "status": "passed"
            },
            "line": 12,
            "name": "the user clicks on the login button",
            "match": {
              "location": "com.spriteCloud.stepDefinitions.SampleAppStepDefinition.the_user_clicks_on_the_login_button()"
            },
            "keyword": "And "
          },
          {
            "result": {
              "duration": 50033700,
              "status": "passed"
            },
            "line": 13,
            "name": "the user should see \"Welcome\" as a success notification",
            "match": {
              "arguments": [
                {
                  "val": "\"Welcome\"",
                  "offset": 20
                }
              ],
              "location": "com.spriteCloud.stepDefinitions.SampleAppStepDefinition.the_user_should_see_as_a_success_notification(java.lang.String)"
            },
            "keyword": "Then "
          }
        ],
        "tags": [
          {
            "name": "@ui"
          },
          {
            "name": "@login"
          }
        ]
      }
    ],
    "name": "Sample App",
    "description": "  US: As a user, I should able to login",
    "id": "sample-app",
    "keyword": "Feature",
    "uri": "file:src/test/resources/features/SampleApp.feature",
    "tags": [
      {
        "name": "@ui",
        "type": "Tag",
        "location": {
          "line": 1,
          "column": 1
        }
      }
    ]
  },
  {
    "line": 2,
    "elements": [
      {
        "start_timestamp": "2022-06-18T21:23:56.514Z",
        "before": [
          {
            "result": {
              "status": "passed"
            },
            "match": {
              "location": "com.spriteCloud.stepDefinitions.Hooks.setUp()"
            }
          }
        ],
        "line": 5,
        "name": "Post request for Store Order",
        "description": "",
        "id": "store;post-request-for-store-order",
        "after": [
          {
            "result": {
              "status": "passed"
            },
            "match": {
              "location": "com.spriteCloud.stepDefinitions.Hooks.tearDown(io.cucumber.java.Scenario)"
            }
          }
        ],
        "type": "scenario",
        "keyword": "Scenario",
        "steps": [
          {
            "result": {
              "duration": 997500,
              "status": "passed"
            },
            "line": 7,
            "name": "the endpoint is \"store/order\"",
            "match": {
              "arguments": [
                {
                  "val": "\"store/order\"",
                  "offset": 16
                }
              ],
              "location": "com.spriteCloud.stepDefinitions.BaseAPIStepDefinition.the_endpoint_is(java.lang.String)"
            },
            "keyword": "Given "
          },
          {
            "result": {
              "status": "passed"
            },
            "line": 8,
            "name": "the request body for post store order following",
            "match": {
              "location": "com.spriteCloud.stepDefinitions.StoreStepDefinitions.the_request_body_for_post_store_order_following(java.util.List\u003cjava.util.Map\u003cjava.lang.String, java.lang.Object\u003e\u003e)"
            },
            "rows": [
              {
                "cells": [
                  "id",
                  "petId",
                  "quantity",
                  "shipDate",
                  "status",
                  "complete"
                ]
              },
              {
                "cells": [
                  "6",
                  "2",
                  "1",
                  "2022-07-18T14:52:13.670+0000",
                  "placed",
                  "true"
                ]
              }
            ],
            "keyword": "And "
          },
          {
            "result": {
              "duration": 581024200,
              "status": "passed"
            },
            "line": 12,
            "name": "I send POST request",
            "match": {
              "location": "com.spriteCloud.stepDefinitions.BaseAPIStepDefinition.i_send_POST_request()"
            },
            "keyword": "When "
          },
          {
            "result": {
              "duration": 960500,
              "status": "passed"
            },
            "line": 13,
            "name": "the status code is 200",
            "match": {
              "arguments": [
                {
                  "val": "200",
                  "offset": 19
                }
              ],
              "location": "com.spriteCloud.stepDefinitions.BaseAPIStepDefinition.the_status_code_is(java.lang.Integer)"
            },
            "keyword": "Then "
          },
          {
            "result": {
              "duration": 26128200,
              "status": "passed"
            },
            "line": 15,
            "name": "the response body for post store order following",
            "match": {
              "location": "com.spriteCloud.stepDefinitions.StoreStepDefinitions.the_response_body_for_post_store_order_following(java.util.List\u003cjava.util.Map\u003cjava.lang.String, java.lang.Object\u003e\u003e)"
            },
            "rows": [
              {
                "cells": [
                  "id",
                  "petId",
                  "status"
                ]
              },
              {
                "cells": [
                  "6",
                  "2",
                  "placed"
                ]
              }
            ],
            "keyword": "And "
          }
        ],
        "tags": [
          {
            "name": "@api"
          },
          {
            "name": "@store"
          }
        ]
      }
    ],
    "name": "Store",
    "description": "",
    "id": "store",
    "keyword": "Feature",
    "uri": "file:src/test/resources/features/Store.feature",
    "tags": [
      {
        "name": "@api",
        "type": "Tag",
        "location": {
          "line": 1,
          "column": 1
        }
      }
    ]
  },
  {
    "line": 2,
    "elements": [
      {
        "start_timestamp": "2022-06-18T21:23:57.127Z",
        "before": [
          {
            "result": {
              "status": "passed"
            },
            "match": {
              "location": "com.spriteCloud.stepDefinitions.Hooks.setUp()"
            }
          }
        ],
        "line": 5,
        "name": "Post request for user",
        "description": "",
        "id": "user;post-request-for-user",
        "after": [
          {
            "result": {
              "status": "passed"
            },
            "match": {
              "location": "com.spriteCloud.stepDefinitions.Hooks.tearDown(io.cucumber.java.Scenario)"
            }
          }
        ],
        "type": "scenario",
        "keyword": "Scenario",
        "steps": [
          {
            "result": {
              "duration": 1012800,
              "status": "passed"
            },
            "line": 7,
            "name": "the endpoint is \"user\"",
            "match": {
              "arguments": [
                {
                  "val": "\"user\"",
                  "offset": 16
                }
              ],
              "location": "com.spriteCloud.stepDefinitions.BaseAPIStepDefinition.the_endpoint_is(java.lang.String)"
            },
            "keyword": "Given "
          },
          {
            "result": {
              "status": "passed"
            },
            "line": 8,
            "name": "the request body for post user following",
            "match": {
              "location": "com.spriteCloud.stepDefinitions.UserStepDefinition.the_request_body_for_post_user_following(java.util.List\u003cjava.util.Map\u003cjava.lang.String, java.lang.Object\u003e\u003e)"
            },
            "rows": [
              {
                "cells": [
                  "id",
                  "username",
                  "firstName",
                  "lastName",
                  "email",
                  "password",
                  "phone",
                  "userStatus"
                ]
              },
              {
                "cells": [
                  "30",
                  "ms",
                  "Mike",
                  "Sun",
                  "ms@mail.com",
                  "123",
                  "1234567",
                  "30"
                ]
              }
            ],
            "keyword": "And "
          },
          {
            "result": {
              "duration": 487916800,
              "status": "passed"
            },
            "line": 12,
            "name": "I send POST request",
            "match": {
              "location": "com.spriteCloud.stepDefinitions.BaseAPIStepDefinition.i_send_POST_request()"
            },
            "keyword": "When "
          },
          {
            "result": {
              "duration": 996300,
              "status": "passed"
            },
            "line": 13,
            "name": "the status code is 200",
            "match": {
              "arguments": [
                {
                  "val": "200",
                  "offset": 19
                }
              ],
              "location": "com.spriteCloud.stepDefinitions.BaseAPIStepDefinition.the_status_code_is(java.lang.Integer)"
            },
            "keyword": "Then "
          },
          {
            "result": {
              "duration": 21969700,
              "status": "passed"
            },
            "line": 14,
            "name": "the response body of user post request following",
            "match": {
              "location": "com.spriteCloud.stepDefinitions.UserStepDefinition.the_response_body_of_user_post_request_following(java.util.List\u003cjava.util.Map\u003cjava.lang.String, java.lang.Object\u003e\u003e)"
            },
            "rows": [
              {
                "cells": [
                  "code",
                  "type",
                  "message"
                ]
              },
              {
                "cells": [
                  "200",
                  "unknown",
                  "30"
                ]
              }
            ],
            "keyword": "And "
          }
        ],
        "tags": [
          {
            "name": "@api"
          },
          {
            "name": "@user"
          }
        ]
      }
    ],
    "name": "User",
    "description": "",
    "id": "user",
    "keyword": "Feature",
    "uri": "file:src/test/resources/features/User.feature",
    "tags": [
      {
        "name": "@api",
        "type": "Tag",
        "location": {
          "line": 1,
          "column": 1
        }
      }
    ]
  },
  {
    "line": 2,
    "elements": [
      {
        "start_timestamp": "2022-06-18T21:23:57.643Z",
        "before": [
          {
            "result": {
              "status": "passed"
            },
            "match": {
              "location": "com.spriteCloud.stepDefinitions.Hooks.setUp()"
            }
          }
        ],
        "line": 6,
        "name": "Verify that the user able to find an element by displayed text has nuances",
        "description": "",
        "id": "verify-text;verify-that-the-user-able-to-find-an-element-by-displayed-text-has-nuances",
        "after": [
          {
            "result": {
              "duration": 707978600,
              "status": "passed"
            },
            "match": {
              "location": "com.spriteCloud.stepDefinitions.Hooks.tearDown(io.cucumber.java.Scenario)"
            }
          }
        ],
        "type": "scenario",
        "keyword": "Scenario",
        "steps": [
          {
            "result": {
              "duration": 3699038800,
              "status": "passed"
            },
            "line": 7,
            "name": "the user is on the page",
            "match": {
              "location": "com.spriteCloud.stepDefinitions.ClickStepDefinition.the_user_is_on_the_page()"
            },
            "keyword": "Given "
          },
          {
            "result": {
              "duration": 339239500,
              "status": "passed"
            },
            "line": 8,
            "name": "the user clicks on the \"Verify Text\" headline",
            "match": {
              "arguments": [
                {
                  "val": "\"Verify Text\"",
                  "offset": 23
                }
              ],
              "location": "com.spriteCloud.stepDefinitions.ClickStepDefinition.the_user_clicks_on_the_headline(java.lang.String)"
            },
            "keyword": "When "
          },
          {
            "result": {
              "duration": 31774400,
              "status": "passed"
            },
            "line": 9,
            "name": "the window title contains \"Verify Text\"",
            "match": {
              "arguments": [
                {
                  "val": "\"Verify Text\"",
                  "offset": 26
                }
              ],
              "location": "com.spriteCloud.stepDefinitions.ClickStepDefinition.the_window_title_contains(java.lang.String)"
            },
            "keyword": "Then "
          },
          {
            "result": {
              "duration": 112617500,
              "status": "passed"
            },
            "line": 10,
            "name": "the user should see the all \"Welcome\" text in the page",
            "match": {
              "arguments": [
                {
                  "val": "\"Welcome\"",
                  "offset": 28
                }
              ],
              "location": "com.spriteCloud.stepDefinitions.VerifyTextStepDefinition.the_user_should_see_the_all_text_in_the_page(java.lang.String)"
            },
            "keyword": "And "
          }
        ],
        "tags": [
          {
            "name": "@ui"
          },
          {
            "name": "@verifyText"
          }
        ]
      }
    ],
    "name": "Verify Text",
    "description": "  US: As a user, I should able to find text",
    "id": "verify-text",
    "keyword": "Feature",
    "uri": "file:src/test/resources/features/VerifyText.feature",
    "tags": [
      {
        "name": "@ui",
        "type": "Tag",
        "location": {
          "line": 1,
          "column": 1
        }
      }
    ]
  }
]